rexpand_pyutils_matching/__init__.py
rexpand_pyutils_matching/matchers.py
rexpand_pyutils_matching/searcher.py
rexpand_pyutils_matching/similarities/__init__.py
rexpand_pyutils_matching/similarities/backup.py
rexpand_pyutils_matching/similarities/bert_score.py
rexpand_pyutils_matching/similarities/common_prefix.py
rexpand_pyutils_matching/similarities/directional_similarity.py
rexpand_pyutils_matching/similarities/levenshtein.py
rexpand_pyutils_matching/similarities/longest_common_sequence.py
rexpand_pyutils_matching/similarities/longest_consecutive_common_sequence.py
rexpand_pyutils_matching/similarities/starts_with.py
rexpand_pyutils_matching/utils/__init__.py
rexpand_pyutils_matching/utils/chatgpt.py
rexpand_pyutils_matching/utils/matching_socre_basics.py
rexpand_pyutils_matching/utils/string.py
rexpand_pyutils_matching-0.0.10.dist-info/METADATA
rexpand_pyutils_matching-0.0.10.dist-info/WHEEL
rexpand_pyutils_matching-0.0.10.dist-info/RECORD
