Metadata-Version: 2.4
Name: rexpand-pyutils-matching
Version: 0.0.10
Summary: Python utilities for string matching
Project-URL: Homepage, https://github.com/expand-app/rexpand-pyutils-matching
Project-URL: Bug Tracker, https://github.com/expand-app/rexpand-pyutils-matching/issues
Author: Shuo Feng
Classifier: License :: OSI Approved :: MIT License
Classifier: Operating System :: OS Independent
Classifier: Programming Language :: Python :: 3
Requires-Python: >=3.11
Requires-Dist: openai>=1.66.3
Provides-Extra: dev
Requires-Dist: black>=23.0.0; extra == 'dev'
Requires-Dist: build>=1.0.0; extra == 'dev'
Requires-Dist: flake8>=6.0.0; extra == 'dev'
Requires-Dist: mypy>=1.0.0; extra == 'dev'
Requires-Dist: pytest>=7.0.0; extra == 'dev'
Requires-Dist: twine>=4.0.0; extra == 'dev'
